c2vb/__init__.py
c2vb/ast.py
c2vb/idt.py
c2vb/lexer.py
c2vb/main.py
c2vb/parser.py
c2vb-0.0.4.dist-info/LICENSE
c2vb-0.0.4.dist-info/METADATA
c2vb-0.0.4.dist-info/WHEEL
c2vb-0.0.4.dist-info/entry_points.txt
c2vb-0.0.4.dist-info/top_level.txt
c2vb-0.0.4.dist-info/RECORD
