Metadata-Version: 2.1
Name: c2vb
Version: 0.0.4
Summary: A program convert simple C / C++ code to Visual Basic 6 code
Home-page: https://github.com/Chaigidel/c2vb
Author: Chaigidel
Author-email: chaigidel@outlook.com
License: MIT
Keywords: c,cpp,visualbasic,ast
Platform: UNKNOWN
Classifier: Programming Language :: Python :: 3
Classifier: License :: OSI Approved :: MIT License
Classifier: Operating System :: OS Independent
